aws_s3_resource/__init__.py
aws_s3_resource/s3_bucket.py
aws_s3_resource/s3_bucket_error.py
aws_s3_resource/s3_object.py
aws_s3_resource-0.0.15.dist-info/LICENSE
aws_s3_resource-0.0.15.dist-info/METADATA
aws_s3_resource-0.0.15.dist-info/WHEEL
aws_s3_resource-0.0.15.dist-info/top_level.txt
aws_s3_resource-0.0.15.dist-info/RECORD
