Metadata-Version: 2.1
Name: aws-s3-resource
Version: 0.0.15
Summary: This library is to ease the operations done on AWS S3 buckets and objects
Home-page: https://github.com/Quakingaspen-codehub/aws_s3_resource
Author: Quaking Aspen
Author-email: info@quakingaspen.net
License: MIT
Platform: UNKNOWN
Classifier: Programming Language :: Python :: 3
Classifier: License :: OSI Approved :: MIT License
Classifier: Operating System :: OS Independent
Requires-Python: >=3.6
License-File: LICENSE
Requires-Dist: boto3
Requires-Dist: botocore
Requires-Dist: pathlib
